unconcealment/__init__.py
unconcealment/config.py
unconcealment/finder.py
unconcealment/main.py
unconcealment/result.py
unconcealment/secret_pattern.py
unconcealment-0.7.1.dist-info/entry_points.txt
unconcealment-0.7.1.dist-info/LICENSE
unconcealment-0.7.1.dist-info/WHEEL
unconcealment-0.7.1.dist-info/METADATA
unconcealment-0.7.1.dist-info/RECORD
