Metadata-Version: 2.1
Name: unconcealment
Version: 0.7.1
Summary: unconcealment
License: GPLv3
Author: adioss
Author-email: adrien.pailhes@outlook.com
Requires-Python: >=3.8,<4.0
Classifier: License :: Other/Proprietary License
Classifier: Programming Language :: Python :: 3
Classifier: Programming Language :: Python :: 3.10
Classifier: Programming Language :: Python :: 3.8
Classifier: Programming Language :: Python :: 3.9
Requires-Dist: argparse (>=1.4.0,<2.0.0)
